say/__init__.py
say/core.py
say/prefixes.py
say/styling.py
say/text.py
say/textrange.py
say/util.py
say/version.py
say/vertical.py
say-1.6.6.dist-info/METADATA
say-1.6.6.dist-info/WHEEL
say-1.6.6.dist-info/top_level.txt
say-1.6.6.dist-info/RECORD
